six2scte35.py
six2scte35-0.0.5.data/scripts/six2scte35
six2scte35-0.0.5.dist-info/LICENSE
six2scte35-0.0.5.dist-info/METADATA
six2scte35-0.0.5.dist-info/WHEEL
six2scte35-0.0.5.dist-info/top_level.txt
six2scte35-0.0.5.dist-info/RECORD
