Metadata-Version: 2.1
Name: six2scte35
Version: 0.0.5
Summary: ffmpeg changes SCTE-35 stream type to 0x6, six2scte35 changes it back
Home-page: https://github.com/futzu/six2scte35
Author: Adrian of Doom
Author-email: spam@iodisco.com
Platform: all
Classifier: License :: OSI Approved :: MIT License
Classifier: Operating System :: OS Independent
Classifier: Programming Language :: Python :: 3.6
Classifier: Programming Language :: Python :: Implementation :: PyPy
Classifier: Programming Language :: Python :: Implementation :: CPython
Requires-Python: >=3.6
License-File: LICENSE
Requires-Dist: new-reader >=0.1.9
Requires-Dist: threefive >=2.4.39
